carconnectivity_homekit/__init__.py
carconnectivity_homekit/carconnectivity_homekit_base.py
carconnectivity_plugin_homekit-0.7.5.dist-info/licenses/LICENSE
carconnectivity_plugins/homekit/__init__.py
carconnectivity_plugins/homekit/_version.py
carconnectivity_plugins/homekit/plugin.py
carconnectivity_plugins/homekit/accessories/__init__.py
carconnectivity_plugins/homekit/accessories/bridge.py
carconnectivity_plugins/homekit/accessories/charging.py
carconnectivity_plugins/homekit/accessories/charging_plug.py
carconnectivity_plugins/homekit/accessories/climatization.py
carconnectivity_plugins/homekit/accessories/custom_characteristics.py
carconnectivity_plugins/homekit/accessories/dummy_accessory.py
carconnectivity_plugins/homekit/accessories/flashing.py
carconnectivity_plugins/homekit/accessories/generic_accessory.py
carconnectivity_plugins/homekit/accessories/locking_system.py
carconnectivity_plugins/homekit/accessories/outside_temperature.py
carconnectivity_plugins/homekit/accessories/util.py
carconnectivity_plugins/homekit/accessories/window_heating.py
carconnectivity_plugins/homekit/ui/plugin_ui.py
carconnectivity_plugins/homekit/ui/templates/homekit/accessories.html
carconnectivity_plugins/homekit/ui/templates/homekit/pairing.html
carconnectivity_plugin_homekit-0.7.5.dist-info/METADATA
carconnectivity_plugin_homekit-0.7.5.dist-info/WHEEL
carconnectivity_plugin_homekit-0.7.5.dist-info/entry_points.txt
carconnectivity_plugin_homekit-0.7.5.dist-info/top_level.txt
carconnectivity_plugin_homekit-0.7.5.dist-info/RECORD
