Metadata-Version: 2.4
Name: carconnectivity-plugin-homekit
Version: 0.7.5
Summary: CarConnectivity plugin for integrating the cars data into the Apple Home ecosystem
Author: Till Steinbach
License-Expression: MIT
Classifier: Development Status :: 3 - Alpha
Classifier: Intended Audience :: End Users/Desktop
Classifier: Intended Audience :: System Administrators
Classifier: Programming Language :: Python :: 3.9
Classifier: Programming Language :: Python :: 3.10
Classifier: Programming Language :: Python :: 3.11
Classifier: Programming Language :: Python :: 3.12
Classifier: Programming Language :: Python :: 3.13
Classifier: Programming Language :: Python :: 3.14
Classifier: Topic :: Utilities
Classifier: Topic :: System :: Monitoring
Classifier: Topic :: Home Automation
Requires-Python: >=3.9
License-File: LICENSE
Requires-Dist: carconnectivity>=0.11.6
Requires-Dist: HAP-python[QRCode]~=5.0.0
Dynamic: license-file
